pyluban.cpython-36m-aarch64-linux-gnu.so
pyluban-1.1.6.dist-info/WHEEL
pyluban-1.1.6.dist-info/METADATA
pyluban-1.1.6.dist-info/top_level.txt
pyluban-1.1.6.dist-info/LICENSE
pyluban-1.1.6.dist-info/RECORD
luban_parser/luban_types.py
luban_parser/luban_parser.py
luban_parser/lubanLexer.py
luban_parser/lubanParser.py
luban_parser/lubanListener.py
luban_parser/__init__.py
luban_parser/luban.py
